dockhand-0.4.0.dist-info/DESCRIPTION.rst
dockhand-0.4.0.dist-info/METADATA
dockhand-0.4.0.dist-info/RECORD
dockhand-0.4.0.dist-info/WHEEL
dockhand-0.4.0.dist-info/entry_points.txt
dockhand-0.4.0.dist-info/metadata.json
dockhand-0.4.0.dist-info/top_level.txt
shipwright/__init__.py
shipwright/base.py
shipwright/build.py
shipwright/cli.py
shipwright/colors.py
shipwright/compat.py
shipwright/container.py
shipwright/dependencies.py
shipwright/docker.py
shipwright/push.py
shipwright/source_control.py
shipwright/tar.py
shipwright/zipper.py
