Metadata-Version: 2.0
Name: dockhand
Version: 0.4.0
Summary: The right way to build, tag and ship shared Docker containers.
Home-page: https://github.com/6si/shipwright/
Author: Scott Robertson
Author-email: scott@6sense.com
License: Apache Software License
Platform: any
Classifier: Programming Language :: Python
Classifier: Programming Language :: Python :: 2
Classifier: Programming Language :: Python :: 2.7
Classifier: Programming Language :: Python :: 3
Classifier: Programming Language :: Python :: 3.4
Classifier: Programming Language :: Python :: 3.5
Classifier: Development Status :: 4 - Beta
Classifier: Natural Language :: English
Classifier: Intended Audience :: Developers
Classifier: License :: OSI Approved :: Apache Software License
Classifier: Operating System :: OS Independent
Classifier: Topic :: Software Development :: Libraries :: Python Modules
Requires-Dist: GitPython (>=2.0.5,<3.0.0)
Requires-Dist: docker-py (>=1.8.1,<2.0.0)
Provides-Extra: testing
Requires-Dist: nose; extra == 'testing'
